polyhattrick/__init__.py
polyhattrick/client/polyhattrick_client.py
polyhattrick/polyhattrick.py
polyhattrick-0.1.0.dist-info/METADATA
polyhattrick-0.1.0.dist-info/WHEEL
polyhattrick-0.1.0.dist-info/entry_points.txt
polyhattrick-0.1.0.dist-info/licenses/LICENSE
polyhattrick-0.1.0.dist-info/RECORD
